ToOrdinal.py
__init__.py
num_to_ordinal-0.0.2.dist-info/LICENSE.txt
num_to_ordinal-0.0.2.dist-info/METADATA
num_to_ordinal-0.0.2.dist-info/WHEEL
num_to_ordinal-0.0.2.dist-info/top_level.txt
num_to_ordinal-0.0.2.dist-info/RECORD
