Metadata-Version: 2.1
Name: num_to_ordinal
Version: 0.0.2
Summary: Paquete para que transforma de numero a ordinal
Author-email: Greivin Gamboa Flores <greivin.gff@gmail.com>
Classifier: Programming Language :: Python :: 3
Classifier: License :: OSI Approved :: MIT License
Classifier: Operating System :: OS Independent
Requires-Python: >=3.9
License-File: LICENSE.txt
